{
  "parent": "minecraft:recipes/root",
  "criteria": {
    "canCraft": {
      "conditions": {
        "items": [
          {
            "items": [
              "exnihiloauto:highly_compressed_gravel"
            ]
          }
        ]
      },
      "trigger": "minecraft:inventory_changed"
    },
    "has_the_recipe": {
      "conditions": {
        "recipe": "exnihiloauto:atomic_compressed_gravel"
      },
      "trigger": "minecraft:recipe_unlocked"
    }
  },
  "requirements": [
    [
      "canCraft",
      "has_the_recipe"
    ]
  ],
  "rewards": {
    "recipes": [
      "exnihiloauto:atomic_compressed_gravel"
    ]
  }
}