{
  "parent": "minecraft:recipes/root",
  "rewards": {
    "recipes": [
      "exnihiloauto:compressed_dust"
    ]
  },
  "criteria": {
    "canCraft": {
      "trigger": "minecraft:inventory_changed",
      "conditions": {
        "items": [
          {
            "item": "exnihilosequentia:dust"
          }
        ]
      }
    },
    "has_the_recipe": {
      "trigger": "minecraft:recipe_unlocked",
      "conditions": {
        "recipe": "exnihiloauto:compressed_dust"
      }
    }
  },
  "requirements": [
    [
      "canCraft",
      "has_the_recipe"
    ]
  ]
}